judge_micro/__init__.py
judge_micro/api/__init__.py
judge_micro/api/main.py
judge_micro/api/models/__init__.py
judge_micro/api/models/judge.py
judge_micro/api/routes/__init__.py
judge_micro/api/routes/heartbeat.py
judge_micro/api/routes/judge.py
judge_micro/config/__init__.py
judge_micro/config/settings.py
judge_micro/docker/__init__.py
judge_micro/docker/client.py
judge_micro/docker/images.py
judge_micro/sdk/__init__.py
judge_micro/sdk/client.py
judge_micro/sdk/docker_ssh.py
judge_micro/services/micro.py
judge_micro-0.0.3.dist-info/METADATA
judge_micro-0.0.3.dist-info/WHEEL
judge_micro-0.0.3.dist-info/licenses/LICENSE
judge_micro-0.0.3.dist-info/RECORD
