Metadata-Version: 2.4
Name: judge_micro
Version: 0.0.3
Author-email: Xuan‑You Lin <a0985821880@gmail.com>
Maintainer-email: Xuan‑You Lin <a0985821880@gmail.com>
License-Expression: Apache-2.0
License-File: LICENSE
Requires-Python: <3.14,>3.8
Requires-Dist: docker
Requires-Dist: fastapi
Requires-Dist: gunicorn
Requires-Dist: httpx
Requires-Dist: paramiko
Requires-Dist: pydantic
Requires-Dist: python-dotenv
Requires-Dist: python-multipart
Requires-Dist: uvicorn[standard]
